nuggetry/__init__.py
nuggetry/builtins.py
nuggetry/interpreter.py
nuggetry/parser.py
nuggetry/repl.py
nuggetry-0.2.dist-info/METADATA
nuggetry-0.2.dist-info/WHEEL
nuggetry-0.2.dist-info/entry_points.txt
nuggetry-0.2.dist-info/top_level.txt
nuggetry-0.2.dist-info/RECORD
